nintendeals/__init__.py
nintendeals/api/__init__.py
nintendeals/api/prices.py
nintendeals/commons/__init__.py
nintendeals/commons/classes/__init__.py
nintendeals/commons/classes/eshops.py
nintendeals/commons/classes/games.py
nintendeals/commons/classes/prices.py
nintendeals/commons/enumerates.py
nintendeals/noa/__init__.py
nintendeals/noa/api/__init__.py
nintendeals/noa/api/algolia.py
nintendeals/noa/info.py
nintendeals/noa/listing.py
nintendeals/noa/scrapers/__init__.py
nintendeals/noa/scrapers/nintendo.py
nintendeals/noa/search.py
nintendeals/noa/util.py
nintendeals/noe/__init__.py
nintendeals/noe/api/__init__.py
nintendeals/noe/api/nintendo.py
nintendeals/noe/info.py
nintendeals/noe/listing.py
nintendeals/noe/search.py
nintendeals/noe/util.py
nintendeals/noj/__init__.py
nintendeals/noj/api/__init__.py
nintendeals/noj/api/nintendo.py
nintendeals/noj/info.py
nintendeals/noj/listing.py
nintendeals/noj/search.py
nintendeals/noj/util.py
nintendeals-3.1.3.dist-info/LICENSE
nintendeals-3.1.3.dist-info/WHEEL
nintendeals-3.1.3.dist-info/METADATA
nintendeals-3.1.3.dist-info/RECORD
