Metadata-Version: 2.1
Name: nintendeals
Version: 3.1.3
Summary: Scraping tools for Nintendo Switch games and prices on NA, EU and JP.
Home-page: https://github.com/fedecalendino/nintendeals
License: MIT
Keywords: nintendo,deals
Author: Fede Calendino
Author-email: fede@calendino.com
Requires-Python: >=3.8,<4.0
Classifier: Intended Audience :: Developers
Classifier: License :: OSI Approved :: MIT License
Classifier: Programming Language :: Python :: 3
Classifier: Programming Language :: Python :: 3.8
Classifier: Programming Language :: Python :: 3.9
Classifier: Programming Language :: Python :: 3.10
Classifier: Programming Language :: Python :: 3.11
Classifier: Programming Language :: Python :: 3.10
Classifier: Programming Language :: Python :: 3.8
Classifier: Programming Language :: Python :: 3.9
Requires-Dist: algoliasearch (>=3.0.0,<4.0.0)
Requires-Dist: beautifulsoup4 (>=4.11.1,<5.0.0)
Requires-Dist: pycountry (>=22.3.5,<23.0.0)
Requires-Dist: python-dateutil (>=2.8.2,<3.0.0)
Requires-Dist: requests (>=2.28.1,<3.0.0)
Requires-Dist: xmltodict (>=0.13.0,<0.14.0)
Project-URL: Documentation, https://github.com/fedecalendino/nintendeals/blob/main/README.md
